microbuildtool/__init__.py
microbuildtool/build.py
microbuildtool/cli.py
microbuildtool/click_utils.py
microbuildtool/collect.py
microbuildtool/command_builder.py
microbuildtool/config.py
microbuildtool-0.3.1.dist-info/METADATA
microbuildtool-0.3.1.dist-info/WHEEL
microbuildtool-0.3.1.dist-info/entry_points.txt
microbuildtool-0.3.1.dist-info/top_level.txt
microbuildtool-0.3.1.dist-info/RECORD
