Metadata-Version: 2.4
Name: microbuildtool
Version: 0.3.1
Summary: J2ME micro build tool
Requires-Python: >=3.12
Requires-Dist: adaptix>=3.0.0b11
Requires-Dist: click>=8.3.1
Requires-Dist: requests>=2.32.5
